README.md
setup.py
CellSpecLR/__init__.py
CellSpecLR.egg-info/PKG-INFO
CellSpecLR.egg-info/SOURCES.txt
CellSpecLR.egg-info/dependency_links.txt
CellSpecLR.egg-info/top_level.txt